{
  "protocol": "YISHEN_GLOBAL_INTEL_FEED_V5",
  "last_sync": "AUTO",
  "heartbeat": 300,
  "dimensions": [
    "FURNITURE",
    "MARITIME_HARDWARE",
    "MEDICAL_PRECISION",
    "INFRA_TOOLS",
    "BIO_MATERIALS",
    "AERO_MILITARY",
    "ACTUATION_SYSTEMS"
  ],
  "intel_nodes": [
    {
      "sku": "OFFICE_MESH_V4",
      "sector": "FURNITURE",
      "hs": "9401.31",
      "market_signal": "HIGH_DEMAND_US_CA_MX",
      "status": "GROWTH_NODE",
      "priority": 1,
      "suggested_action": "EXPAND_CHANNELS",
      "next_patch": "PACKING_OPTIMIZATION"
    },
    {
      "sku": "CHAIN_G80_MASTER",
      "sector": "MARITIME_HARDWARE",
      "hs": "7315.82",
      "market_signal": "BRAZIL_AD_EXEMPT",
      "status": "EXPORT_FAST_LANE",
      "priority": 2,
      "suggested_action": "SANTOS_NODE_ROUTING",
      "next_patch": "FORM_E_CERT"
    },
    {
      "sku": "MEDICAL_CHAIR_X9",
      "sector": "MEDICAL_PRECISION",
      "hs": "9402.10",
      "market_signal": "ASEAN_ZERO_TARIFF",
      "status": "CLINIC_FAST_ENTRY",
      "priority": 3,
      "suggested_action": "STERILE_PACK_PATCH",
      "next_patch": "ISO_13485"
    },
    {
      "sku": "INFRA_LADDER_PRO",
      "sector": "INFRA_TOOLS",
      "hs": "7616.99",
      "market_signal": "NA_INFRA_TARIFF_WALL",
      "status": "TARIFF_DEFENSE",
      "priority": 4,
      "suggested_action": "ASEAN_BYPASS_NODE",
      "next_patch": "EN131_UPGRADE"
    },
    {
      "sku": "CARBON_PANEL_BIOX",
      "sector": "BIO_MATERIALS",
      "hs": "6810.11",
      "market_signal": "EU_GREEN_MANDATE",
      "status": "CARBON_NEUTRAL_NODE",
      "priority": 5,
      "suggested_action": "ECO_CERT_STACK",
      "next_patch": "EPD_DECLARATION"
    }
  ],
  "growth_directives": {
    "auto_patch": true,
    "auto_extend_sku": true,
    "auto_write_sitemap": true,
    "auto_expand_clusters": true
  }
}
